pytorch_focalloss-1.2.0.dist-info/licenses/LICENSE
torch_focalloss/__init__.py
torch_focalloss/losses.py
torch_focalloss/py.typed
pytorch_focalloss-1.2.0.dist-info/METADATA
pytorch_focalloss-1.2.0.dist-info/WHEEL
pytorch_focalloss-1.2.0.dist-info/top_level.txt
pytorch_focalloss-1.2.0.dist-info/RECORD
