Metadata-Version: 2.4
Name: pytorch-focalloss
Version: 1.2.0
Summary: PyTorch implementations of binary and multi-class focal loss
Author-email: Danny Collinson <dannycollinson12@gmail.com>
Maintainer-email: Danny Collinson <dannycollinson12@gmail.com>
License-Expression: MIT
Project-URL: Homepage, https://github.com/dannycollinson/pytorch-focalloss
Project-URL: Repository, https://github.com/dannycollinson/pytorch-focalloss
Project-URL: Issues, https://github.com/dannycollinson/pytorch-focalloss/issues
Keywords: focal loss,pytorch,loss,function,focal
Classifier: Development Status :: 4 - Beta
Classifier: Intended Audience :: Developers
Classifier: Natural Language :: English
Classifier: Programming Language :: Python :: 3
Classifier: Operating System :: OS Independent
Classifier: Topic :: Scientific/Engineering :: Artificial Intelligence
Requires-Python: >=3.8
License-File: LICENSE
Requires-Dist: torch>=1.10.0
Dynamic: license-file
